MANIFEST.in
README.md
pytest_pride.py
setup.py
pytest_pride.egg-info/PKG-INFO
pytest_pride.egg-info/SOURCES.txt
pytest_pride.egg-info/dependency_links.txt
pytest_pride.egg-info/entry_points.txt
pytest_pride.egg-info/requires.txt
pytest_pride.egg-info/top_level.txt