Metadata-Version: 1.1
Name: pytest-pride
Version: 0.1.2
Summary: Minitest-style test colors
Home-page: https://github.com/meunierd/pytest-pride
Author: Devon Meunier
Author-email: devon.meunier@gmail.com
License: MIT
Platform: UNKNOWN
Classifier: Development Status :: 3 - Alpha
Classifier: Topic :: Software Development :: Testing
Classifier: Intended Audience :: Developers
Classifier: Operating System :: OS Independent
